Workbook

Sheet Planilha1
B1: CNPJ2 | C1: CEG | D1: Usina
A2: 121 | B2: =VLOOKUP($C2,Planilha2!$B:$E,4,FALSE) -> 10618009000114 | C2: 31598 | D2: ADOPOPINHAK
A3: 14056 | B3: 23.865.997/0001-48 | C3: 29555 | D3: AREMBEPE
A4: 20295 | B4: =VLOOKUP($C4,Planilha2!$B:$E,4,FALSE) -> 330001670001E5 | C4: 1096 | D4: AURELIANOCHAVES(ANTIGAIBIRITE)
A5: 2190 | B5: =VLOOKUP($C5,Planilha2!$B:$E,4,FALSE) -> 07799995000141 | C5: 29453 | D5: BAGUARI-COTABAGUARII
A6: 754 | B6: =VLOOKUP($C6,Planilha2!$B:$E,4,FALSE) -> 07799995000141 | C6: 29453 | D6: BAGUARI-COTACEMIG
A7: 741 | B7: =VLOOKUP($C7,Planilha2!$B:$E,4,FALSE) -> 07799995000141 | C7: 29453 | D7: BAGUARI-COTAFURNAS
A8: 2703 | B8: 23.865.997/0001-48 | C8: 28615 | D8: BAHIAI
A9: 310134 | B9: =VLOOKUP($C9,Planilha2!$B:$E,4,FALSE) -> 330001670001E5 | C9: 27952 | D9: BARBOSALIMASOBRINHO
A10: 113106 | B10: =VLOOKUP($C10,Planilha2!$B:$E,4,FALSE) -> 330001670001E5 | C10: 27952 | D10: BARBOSALIMASOBRINHO(ANTIGAELETROBOLT)
A11: 230 | B11: 12.300.288/0001-07 | C11: 30354 | D11: BELOMONTE2
A12: 646 | B12: =VLOOKUP($C12,Planilha2!$B:$E,4,FALSE) -> 23857764000101 | C12: 33467 | D12: BOLTBAH
A13: 456 | B13: 23.865.997/0001-48 | C13: 29554 | D13: CAMACARIMURICYI
A14: 454 | B14: 23.865.997/0001-48 | C14: 29555 | D14: CAMACARIPOLODEAPOIOI
A15: 2338 | B15: =VLOOKUP($C15,Planilha2!$B:$E,4,FALSE) -> 02016507000169 | C15: 29767 | D15: CANDIOTAIII(FASECDAUSINATERMELETRICAPRESIDENTEMEDICI)
A16: 476 | B16: =VLOOKUP($C16,Planilha2!$B:$E,4,FALSE) -> 15394399000100 | C16: 30897 | D16: CARCARA2
A17: 3266 | B17: =VLOOKUP($C17,Planilha2!$B:$E,4,FALSE) -> 330001670001E5 | C17: 27263 | D17: CELSOFURTADO
A18: 115991 | B18: =VLOOKUP($C18,Planilha2!$B:$E,4,FALSE) -> 330001670001E5 | C18: 27263 | D18: CELSOFURTADO(ANTIGATERMOBAHIAFASEI)
A19: 531 | B19: 76.321.496/0001-67 | C19: 27978 | D19: CISFRAMA
A20: 633 | B20: =VLOOKUP($C20,Planilha2!$B:$E,4,FALSE) -> 330001670001E5 | C20: 28014 | D20: CUBATAO
A21: 317 | B21: =VLOOKUP($C21,Planilha2!$B:$E,4,FALSE) -> 23598517000120 | C21: 33682 | D21: DELTA3I
A22: 383 | B22: =VLOOKUP($C22,Planilha2!$B:$E,4,FALSE) -> 23598858000103 | C22: 33683 | D22: DELTA3II
A23: 933 | B23: =VLOOKUP($C23,Planilha2!$B:$E,4,FALSE) -> 23598847000115 | C23: 33684 | D23: DELTA3III
A24: 2361 | B24: =VLOOKUP($C24,Planilha2!$B:$E,4,FALSE) -> 23598842000192 | C24: 33685 | D24: DELTA3IV
A25: 627 | B25: =VLOOKUP($C25,Planilha2!$B:$E,4,FALSE) -> 23598829000133 | C25: 33675 | D25: DELTA3V
A26: 695 | B26: =VLOOKUP($C26,Planilha2!$B:$E,4,FALSE) -> 23598831000102 | C26: 33673 | D26: DELTA3VI
A27: 714 | B27: =VLOOKUP($C27,Planilha2!$B:$E,4,FALSE) -> 23598844000181 | C27: 33680 | D27: DELTA3VII
A28: 354 | B28: =VLOOKUP($C28,Planilha2!$B:$E,4,FALSE) -> 05620523000235 | C28: 29193 | D28: ELDORADOAMPLIACAO
A29: 667 | B29: =VLOOKUP($C29,Planilha2!$B:$E,4,FALSE) -> 330001670001E5 | C29: 27952 | D29: ELETROBOLT
A30: 310200 | B30: =VLOOKUP($C30,Planilha2!$B:$E,4,FALSE) -> 330001670001E5 | C30: 28014 | D30: EUZEBIOROCHA
A31: 113018 | B31: =VLOOKUP($C31,Planilha2!$B:$E,4,FALSE) -> 330001670001E5 | C31: 28014 | D31: EUZEBIOROCHA(ANTIGACUBATAO-CCBS)
... A45: 2197 | B45: =VLOOKUP($C45,Planilha2!$B:$E,4,FALSE) -> 09029666000147 | C45: 29736 | D45: JIRAU-AMPLIACAO
A46: 742 | B46: 3460864000184 | C46: 1304 | D46: LAJEADOI
A47: 2776 | B47: 3460864000184 | C47: 1304 | D47: LAJEADOII
A48: 745 | B48: 3460864000184 | C48: 1304 | D48: LAJEADOIII
A49: 2157 | B49: =VLOOKUP($C49,Planilha2!$B:$E,4,FALSE) -> 15527906000136 | C49: 29717 | D49: LDCBIOENERGIALAGOADAPRATA
A50: 1301 | B50: =VLOOKUP($C50,Planilha2!$B:$E,4,FALSE) -> 15527906000136 | C50: 29718 | D50: LDCBIOENERGIARIOBRILHANTE
A51: 675 | B51: =VLOOKUP($C51,Planilha2!$B:$E,4,FALSE) -> 10472905000118 | C51: 30054 | D51: LINHARES
A52: 310136 | B52: =VLOOKUP($C52,Planilha2!$B:$E,4,FALSE) -> 330001670001E5 | C52: 27975 | D52: LUISCARLOSPRESTES
A53: 113736 | B53: =VLOOKUP($C53,Planilha2!$B:$E,4,FALSE) -> 330001670001E5 | C53: 27975 | D53: LUIZCARLOSPRESTES(ANTIGATRESLAGOAS)
A54: 3280 | B54: =VLOOKUP($C54,Planilha2!$B:$E,4,FALSE) -> 330001670001E5 | C54: 28029 | D54: MACAEMERCHANT
A55: 265 | B55: =VLOOKUP($C55,Planilha2!$B:$E,4,FALSE) -> 05643940000112 | C55: 30572 | D55: MANOPLA
A56: 2411 | B56: =VLOOKUP($C56,Planilha2!$B:$E,4,FALSE) -> 15743303000171 | C56: 30202 | D56: MARANHAOIV
A57: 1340 | B57: =VLOOKUP($C57,Planilha2!$B:$E,4,FALSE) -> 15743303000171 | C57: 30203 | D57: MARANHAOV
A58: 112907 | B58: =VLOOKUP($C58,Planilha2!$B:$E,4,FALSE) -> 330001670001E5 | C58: 28029 | D58: MARIOLAGO(ANTIGAMACAEMERCHANT)
A59: 951 | B59: =VLOOKUP($C59,Planilha2!$B:$E,4,FALSE) -> 02016507000169 | C59: 29598 | D59: MAUA
A60: 14060 | B60: 23.865.997/0001-48 | C60: 29554 | D60: MURICY
A61: 961 | B61: =VLOOKUP($C61,Planilha2!$B:$E,4,FALSE) -> 23449511000190 | C61: 32955 | D61: NOVOTEMPO
A62: 112918 | B62: =VLOOKUP($C62,Planilha2!$B:$E,4,FALSE) -> 23449511000190 | C62: 32955 | D62: NOVOTEMPOGNAII
A63: 908 | B63: =VLOOKUP($C63,Planilha2!$B:$E,4,FALSE) -> 15231615000104 | C63: 31015 | D63: PARQUEEOLICOCABECOPRETOIII
A64: 904 | B64: =VLOOKUP($C64,Planilha2!$B:$E,4,FALSE) -> 15231547000175 | C64: 30876 | D64: PARQUEEOLICOCABECOPRETOV
A65: 102 | B65: =VLOOKUP($C65,Planilha2!$B:$E,4,FALSE) -> 15231479000144 | C65: 30900 | D65: PARQUEEOLICOCABECOPRETOVI
A66: 2712 | B66: =VLOOKUP($C66,Planilha2!$B:$E,4,FALSE) -> 04735629000130 | C66: 28533 | D66: PECEM
A67: 2205 | B67: =VLOOKUP($C67,Planilha2!$B:$E,4,FALSE) -> 08322396000103 | C67: 55534 | D67: PORTODASAGUAS(IIFASE)
A68: 557 | B68: =VLOOKUP($C68,Planilha2!$B:$E,4,FALSE) -> 08219477000174 | C68: 29700 | D68: PORTODOITAQUI
A69: 1296 | B69: =VLOOKUP($C69,Planilha2!$B:$E,4,FALSE) -> 08976495000109 | C69: 29720 | D69: PORTOPECEMI
A70: 577 | B70: =VLOOKUP($C70,Planilha2!$B:$E,4,FALSE) -> 60933603000178 | C70: 2127 | D70: PORTOPRIMAVERA
A71: 982 | B71: =VLOOKUP($C71,Planilha2!$B:$E,4,FALSE) -> 60933603000178 | C71: 2127 | D71: PORTOPRIMAVERA(ENG.SERGIOMOTTA)
A72: 284 | B72: =VLOOKUP($C72,Planilha2!$B:$E,4,FALSE) -> 06315338000119 | C72: 29655 | D72: POTIRENDABA
... A91: 216 | B91: =VLOOKUP($C91,Planilha2!$B:$E,4,FALSE) -> 08435796000117 | C91: 28654 | D91: XAVANTEARUANA
A92: 0 | B92: 4232314000170 | C92: 1975 | D92: CEBGERA_PARANOA-DSP1395_2019

Sheet Planilha2
A1: CodCEG | B1: idEmpreendimento | C1: TipoGeracao | D1: NomeEmpreendimento | E1: NumCpfCNPJ | F1: RazaoSocialPj | G1: Participacao | H1: TipoAgente | I1: DtEncerramentoPj | J1: Status | K1: Conforme | L1: ConformeSFG | M1: DescFaseUsina
A2: UFV.RS.MG.047249-2.01 | B2: 47249 | C2: UFV | D2: Alegre II | F2: EDN PROJETOS RENOVÁVEIS E CONSULTORIA LTDA | G2: 100 | H2: PJ | J2: Normal | K2: Sim | L2: Não | M2: Construção não iniciada
A3: UHE.PH.RS.000012-4.01 | B3: 12 | C3: UHE | D3: 14 de Julho | E3: 04237975000199 | F3: COMPANHIA ENERGÉTICA RIO DAS ANTAS | G3: 100 | H3: PJ | J3: Normal | K3: Sim | L3: Sim | M3: Operação
A4: UTE.PE.SC.029920-0.01 | B4: 29920 | C4: UTE | D4: 29 de Outubro | E4: 06538308000171 | F4: Condomínio Residencial 29 de Outubro | G4: 100 | H4: PJ | J4: Normal | K4: Sim | L4: Sim | M4: Operação
A5: UTE.FL.RS.048608-6.01 | B5: 48608 | C5: UTE | D5: 3 Tentos Ijuí | F5: TRÊS TENTOS AGROINDUSTRIAL S.A. | G5: 100 | H5: PJ | J5: Normal | K5: Sim | L5: Sim | M5: Operação
A6: UTE.PE.MG.032686-0.01 | B6: 32686 | C6: UTE | D6: 300KVA SCANIA | E6: 23640204000192 | F6: Mineração Curimbaba Ltda. | G6: 100 | H6: PJ | J6: Normal | K6: Sim | L6: Sim | M6: Operação
A7: UTE.PE.SP.028642-7.01 | B7: 28642 | C7: UTE | D7: 3M Itapetininga | E7: 459853710006E3 | F7: 3M do Brasil Ltda | G7: 100 | H7: PJ | J7: Normal | K7: Sim | L7: Sim | M7: Operação
A8: UTE.PE.SP.028919-1.01 | B8: 28919 | C8: UTE | D8: 3M Sumaré | E8: 459853710006E3 | F8: 3M do Brasil Ltda | G8: 100 | H8: PJ | J8: Normal | K8: Sim | L8: Sim | M8: Operação
A9: PCH.PH.MS.037568-3.01 | B9: 37568 | C9: PCH | D9: A | F9: ENERGÉTICA DAS EMAS LTDA | G9: 100 | H9: PJ | J9: Normal | K9: Sim | L9: Não | M9: Construção não iniciada
A10: UTE.PE.AC.032707-7.01 | B10: 32707 | C10: UTE | D10: A.C.D.A. IMPORTAÇÃO E EXPORTAÇÃO - AMAPÁ | E10: 84308980000184 | F10: A.C.D.A. Importação e exportação Ltda | G10: 100 | H10: PJ | J10: Normal | K10: Sim | L10: Sim | M10: Operação
A11: UTE.PE.AC.032725-5.01 | B11: 32725 | C11: UTE | D11: A.C.D.A. IMPORTAÇÃO E EXPORTAÇÃO - AVIÁRIO | E11: 84308980000184 | F11: A.C.D.A. Importação e exportação Ltda | G11: 100 | H11: PJ | J11: Normal | K11: Sim | L11: Sim | M11: Operação
A12: UTE.PE.AC.032728-0.01 | B12: 32728 | C12: UTE | D12: A.C.D.A. IMPORTAÇÃO E EXPORTAÇÃO - BOSQUE | E12: 84308980000184 | F12: A.C.D.A. Importação e exportação Ltda | G12: 100 | H12: PJ | J12: Normal | K12: Sim | L12: Sim | M12: Operação
A13: UTE.PE.AC.032704-2.01 | B13: 32704 | C13: UTE | D13: A.C.D.A. IMPORTAÇÃO E EXPORTAÇÃO - CHICO MENDES | E13: 84308980000184 | F13: A.C.D.A. Importação e exportação Ltda | G13: 100 | H13: PJ | J13: Normal | K13: Sim | L13: Sim | M13: Operação
A14: UTE.PE.AC.032701-8.01 | B14: 32701 | C14: UTE | D14: A.C.D.A. IMPORTAÇÃO E EXPORTAÇÃO - MIX | E14: 84308980000184 | F14: A.C.D.A. Importação e exportação Ltda | G14: 100 | H14: PJ | J14: Normal | K14: Sim | L14: Sim | M14: Operação
A15: UTE.PE.RO.032731-0.01 | B15: 32731 | C15: UTE | D15: A.C.D.A. IMPORTAÇÃO E EXPORTAÇÃO - PVH | E15: 84308980000184 | F15: A.C.D.A. Importação e exportação Ltda | G15: 100 | H15: PJ | J15: Normal | K15: Sim | L15: Sim | M15: Operação
A16: UTE.PE.AC.032874-0.01 | B16: 32874 | C16: UTE | D16: A.C.D.A. IMPORTAÇÃO E EXPORTAÇÃO - RIO DE JANEIRO | E16: 84308980000184 | F16: A.C.D.A. Importação e exportação Ltda | G16: 100 | H16: PJ | J16: Normal | K16: Sim | L16: Sim | M16: Operação
A17: UTE.PE.AC.032775-1.01 | B17: 32775 | C17: UTE | D17: A.C.D.A. IMPORTAÇÃO E EXPORTAÇÃO - VAREJÃO | E17: 84308980000184 | F17: A.C.D.A. Importação e exportação Ltda | G17: 100 | H17: PJ | J17: Normal | K17: Sim | L17: Sim | M17: Operação
A18: UTE.PE.GO.028991-4.01 | B18: 28991 | C18: UTE | D18: Abatedouro São Salvador | E18: 03387396000160 | F18: SAO SALVADOR ALIMENTOS S/A | G18: 100 | H18: PJ | J18: Normal | K18: Sim | L18: Sim | M18: Operação
A19: CGH.PH.RS.000015-9.01 | B19: 15 | C19: CGH | D19: Abaúna | E19: 11192351000168 | F19: Cooperativa de Geração de Energia e Desenvolvimento | G19: 100 | H19: PJ | J19: Normal | K19: Sim | L19: Sim | M19: Operação
A20: UTE.PE.MG.030905-2.01 | B20: 30905 | C20: UTE | D20: ABC | E20: 041496370002E3 | F20: Adição Distribuição Express Ltda. | G20: 100 | H20: PJ | J20: Normal | K20: Sim | L20: Sim | M20: Operação
A21: UTE.PE.MG.031170-7.01 | B21: 31170 | C21: UTE | D21: ABC | E21: 041496370002E3 | F21: Adição Distribuição Express Ltda. | G21: 100 | H21: PJ | J21: Normal | K21: Sim | L21: Sim | M21: Operação
... A58: UFV.RS.PA.045619-5.01 | B58: 45619 | C58: UFV | D58: Acacio Azevedo de Sousa | E58: 04895728000180 | F58: EQUATORIAL PARÁ DISTRIBUIDORA DE ENERGIA S.A. | G58: 100 | H58: PJ | J58: Normal | K58: Sim | L58: Sim | M58: Operação
A59: UFV.RS.PA.055537-1.01 | B59: 55537 | C59: UFV | D59: Açaí Tapajós | F59: Açaí Tapajós Industria e Comercio Eireli | G59: 100 | H59: PJ | J59: Normal | K59: Sim | L59: Sim | M59: Operação
A60: UFV.RS.PA.055102-3.01 | B60: 55102 | C60: UFV | D60: Acassia Rodrigues Lima | E60: 04895728000180 | F60: EQUATORIAL PARÁ DISTRIBUIDORA DE ENERGIA S.A. | G60: 100 | H60: PJ | J60: Normal | K60: Sim | L60: Sim | M60: Operação
A61: EOL.CV.BA.031433-1.01 | B61: 31433 | C61: EOL | D61: Acauã | E61: 33541368000116 | F61: COMPANHIA HIDRO ELÉTRICA DO SÃO FRANCISCO | G61: 100 | H61: PJ | J61: Normal | K61: Sim | L61: Sim | M61: Operação
A62: UFV.RS.RN.034436-2.01 | B62: 34436 | C62: UFV | D62: Acauã 1 | F62: Acauã Solar Energia SPE Ltda. | G62: 100 | H62: PJ | J62: Normal | K62: Sim | L62: Não | M62: Construção não iniciada
A63: EOL.CV.RN.033597-5.01 | B63: 33597 | C63: EOL | D63: Acauã I | E63: 35842703000141 | F63: CENTRAL EÓLICA ACAUÃ I S.A. | G63: 100 | H63: PJ | J63: Normal | K63: Sim | L63: Sim | M63: Construção
A64: EOL.CV.RN.033598-3.01 | B64: 33598 | C64: EOL | D64: Acauã II | E64: 35842703000141 | F64: CENTRAL EÓLICA ACAUÃ I S.A. | G64: 100 | H64: PJ | J64: Normal | K64: Sim | L64: Sim | M64: Construção
A65: EOL.CV.RN.033864-8.01 | B65: 33864 | C65: EOL | D65: Acauã III | E65: 35842711000198 | F65: CENTRAL EÓLICA ACAUÃ III S.A. | G65: 100 | H65: PJ | J65: Normal | K65: Sim | L65: Sim | M65: Construção
A66: UTE.PE.AC.030904-4.01 | B66: 30904 | C66: UTE | D66: ACDA | E66: 84308980000184 | F66: A.C.D.A. Importação e exportação Ltda | G66: 100 | H66: PJ | J66: Normal | K66: Sim | L66: Sim | M66: Operação
A67: CGH.PH.SC.030419-0.01 | B67: 30419 | C67: CGH | D67: Acearia Frederico Missner (Antiga Rio Luiz Alves) | E67: 82719956000102 | F67: Acearia Frederico Missner S.A | G67: 100 | H67: PJ | J67: Normal | K67: Sim | L67: Sim | M67: Operação
A68: UFV.RS.PA.042942-2.01 | B68: 42942 | C68: UFV | D68: Aceel Gil de Freitas | E68: 04895728000180 | F68: EQUATORIAL PARÁ DISTRIBUIDORA DE ENERGIA S.A. | G68: 100 | H68: PJ | J68: Normal | K68: Sim | L68: Sim | M68: Operação
A69: UFV.RS.PA.039798-9.01 | B69: 39798 | C69: UFV | D69: Acenildo Castro de Lima | E69: 04895728000180 | F69: EQUATORIAL PARÁ DISTRIBUIDORA DE ENERGIA S.A. | G69: 100 | H69: PJ | J69: Normal | K69: Sim | L69: Sim | M69: Operação
A70: UFV.RS.PA.042943-0.01 | B70: 42943 | C70: UFV | D70: Acivaldo Souza Peixoto | E70: 04895728000180 | F70: EQUATORIAL PARÁ DISTRIBUIDORA DE ENERGIA S.A. | G70: 100 | H70: PJ | J70: Normal | K70: Sim | L70: Sim | M70: Operação
A71: UTE.CM.MG.000019-1.01 | B71: 19 | C71: UTE | D71: Açominas | E71: 172274220001E4 | F71: GERDAU AÇOMINAS S/A | G71: 100 | H71: PJ | J71: Normal | K71: Sim | L71: Sim | M71: Operação
A72: PCH.PH.PR.035550-0.01 | B72: 35550 | C72: PCH | D72: Açungui 2E | E72: 81172264000124 | F72: TRANSLEAD EMPREENDIMENTOS E INCORPORAÇÕES LTDA | G72: 100 | H72: PJ | J72: Normal | K72: Sim | L72: Não | M72: Construção não iniciada
A73: PCH.PH.PR.036917-9.01 | B73: 36917 | C73: PCH | D73: Açungui 2F | E73: 81172264000124 | F73: TRANSLEAD EMPREENDIMENTOS E INCORPORAÇÕES LTDA | G73: 100 | H73: PJ | J73: Normal | K73: Sim | L73: Não | M73: Construção não iniciada
A74: UFV.RS.PA.061365-7.01 | B74: 61365 | C74: UFV | D74: Ada Alves da Conseicao | E74: 04895728000180 | F74: EQUATORIAL PARÁ DISTRIBUIDORA DE ENERGIA S.A. | G74: 100 | H74: PJ | J74: Normal | K74: Sim | L74: Sim | M74: Operação
... A253: UFV.RS.PA.039134-4.01 | B253: 39134 | C253: UFV | D253: Aduzinda Abreu Dias | E253: 04895728000180 | F253: EQUATORIAL PARÁ DISTRIBUIDORA DE ENERGIA S.A. | G253: 100 | H253: PJ | J253: Normal | K253: Sim | L253: Sim | M253: Operação
A254: UTE.PE.RS.029380-6.01 | B254: 29380 | C254: UTE | D254: Aeroporto de Bagé | G254: 100 | K254: Sim | L254: Sim | M254: Operação
A255: UTE.PE.RS.029380-6.01 | B255: 29380 | C255: UTE | D255: Aeroporto de Bagé | E255: 003522940002E3 | F255: Empresa Brasileira de Infra-Estrutura Aeroportuária | G255: 100 | H255: PJ | J255: Normal | K255: Sim | L255: Sim | M255: Operação
A256: UTE.PE.MG.029475-6.01 | B256: 29475 | C256: UTE | D256: Aeroporto de Belo Horizonte - Pampulha I | G256: 100 | K256: Sim | L256: Sim | M256: Operação
A257: UTE.PE.MG.029475-6.01 | B257: 29475 | C257: UTE | D257: Aeroporto de Belo Horizonte - Pampulha I | E257: 003522940002E3 | F257: Empresa Brasileira de Infra-Estrutura Aeroportuária | G257: 100 | H257: PJ | J257: Normal | K257: Sim | L257: Sim | M257: Operação
A258: UTE.PE.MG.029476-4.01 | B258: 29476 | C258: UTE | D258: Aeroporto de Belo Horizonte - Pampulha II | G258: 100 | K258: Sim | L258: Sim | M258: Operação
A259: UTE.PE.MG.029476-4.01 | B259: 29476 | C259: UTE | D259: Aeroporto de Belo Horizonte - Pampulha II | E259: 003522940002E3 | F259: Empresa Brasileira de Infra-Estrutura Aeroportuária | G259: 100 | H259: PJ | J259: Normal | K259: Sim | L259: Sim | M259: Operação
A260: UTE.PE.MG.029477-2.01 | B260: 29477 | C260: UTE | D260: Aeroporto de Belo Horizonte - Pampulha III | G260: 100 | K260: Sim | L260: Sim | M260: Operação
A261: UTE.PE.MG.029477-2.01 | B261: 29477 | C261: UTE | D261: Aeroporto de Belo Horizonte - Pampulha III | E261: 003522940002E3 | F261: Empresa Brasileira de Infra-Estrutura Aeroportuária | G261: 100 | H261: PJ | J261: Normal | K261: Sim | L261: Sim | M261: Operação
A262: UTE.PE.SP.029336-9.01 | B262: 29336 | C262: UTE | D262: Aeroporto de Campo de Marte | G262: 100 | K262: Sim | L262: Sim | M262: Operação
A263: UTE.PE.SP.029336-9.01 | B263: 29336 | C263: UTE | D263: Aeroporto de Campo de Marte | E263: 003522940002E3 | F263: Empresa Brasileira de Infra-Estrutura Aeroportuária | G263: 100 | H263: PJ | J263: Normal | K263: Sim | L263: Sim | M263: Operação
A264: UTE.PE.RJ.029451-9.01 | B264: 29451 | C264: UTE | D264: Aeroporto de Campos - SBCP | G264: 100 | K264: Sim | L264: Sim | M264: Operação
A265: UTE.PE.RJ.029451-9.01 | B265: 29451 | C265: UTE | D265: Aeroporto de Campos - SBCP | E265: 003522940002E3 | F265: Empresa Brasileira de Infra-Estrutura Aeroportuária | G265: 100 | H265: PJ | J265: Normal | K265: Sim | L265: Sim | M265: Operação
A266: UTE.PE.MG.029450-0.01 | B266: 29450 | C266: UTE | D266: Aeroporto de Carlos Prates | G266: 100 | K266: Sim | L266: Sim | M266: Operação
A267: UTE.PE.MG.029450-0.01 | B267: 29450 | C267: UTE | D267: Aeroporto de Carlos Prates | E267: 003522940002E3 | F267: Empresa Brasileira de Infra-Estrutura Aeroportuária | G267: 100 | H267: PJ | J267: Normal | K267: Sim | L267: Sim | M267: Operação
A268: UTE.PE.RJ.029444-6.01 | B268: 29444 | C268: UTE | D268: Aeroporto de Jacarepaguá | G268: 100 | K268: Sim | L268: Sim | M268: Operação
A269: UTE.PE.RJ.029444-6.01 | B269: 29444 | C269: UTE | D269: Aeroporto de Jacarepaguá | E269: 003522940002E3 | F269: Empresa Brasileira de Infra-Estrutura Aeroportuária | G269: 100 | H269: PJ | J269: Normal | K269: Sim | L269: Sim | M269: Operação
A270: UTE.PE.SC.029338-5.01 | B270: 29338 | C270: UTE | D270: Aeroporto de Joinville | G270: 100 | K270: Sim | L270: Sim | M270: Operação
A271: UTE.PE.SC.029338-5.01 | B271: 29338 | C271: UTE | D271: Aeroporto de Joinville | E271: 003522940002E3 | F271: Empresa Brasileira de Infra-Estrutura Aeroportuária | G271: 100 | H271: PJ | J271: Normal | K271: Sim | L271: Sim | M271: Operação
A272: UTE.PE.MG.029469-1.01 | B272: 29469 | C272: UTE | D272: Aeroporto de Juiz de Fora | G272: 100 | K272: Sim | L272: Sim | M272: Operação
A273: UTE.PE.MG.029469-1.01 | B273: 29469 | C273: UTE | D273: Aeroporto de Juiz de Fora | E273: 003522940002E3 | F273: Empresa Brasileira de Infra-Estrutura Aeroportuária | G273: 100 | H273: PJ | J273: Normal | K273: Sim | L273: Sim | M273: Operação
A274: UTE.PE.PR.029350-4.01 | B274: 29350 | C274: UTE | D274: Aeroporto de Londrina | G274: 100 | K274: Sim | L274: Sim | M274: Operação
A275: UTE.PE.PR.029350-4.01 | B275: 29350 | C275: UTE | D275: Aeroporto de Londrina | E275: 003522940002E3 | F275: Empresa Brasileira de Infra-Estrutura Aeroportuária | G275: 100 | H275: PJ | J275: Normal | K275: Sim | L275: Sim | M275: Operação
A276: UTE.PE.RJ.029471-3.01 | B276: 29471 | C276: UTE | D276: Aeroporto de Macaé | G276: 100 | K276: Sim | L276: Sim | M276: Operação
A277: UTE.PE.RJ.029471-3.01 | B277: 29471 | C277: UTE | D277: Aeroporto de Macaé | E277: 003522940002E3 | F277: Empresa Brasileira de Infra-Estrutura Aeroportuária | G277: 100 | H277: PJ | J277: Normal | K277: Sim | L277: Sim | M277: Operação
A278: UTE.GN.AL.029375-0.01 | B278: 29375 | C278: UTE | D278: Aeroporto de Maceió | E278: 34274233000102 | F278: PETROBRÁS DISTRIBUIDORA S.A | G278: 100 | H278: PJ | J278: Normal | K278: Sim | L278: Sim | M278: Operação
A279: UTE.PE.MG.029496-9.01 | B279: 29496 | C279: UTE | D279: Aeroporto de Montes Claros - Mário Ribeiro | G279: 100 | K279: Sim | L279: Sim | M279: Operação
A280: UTE.PE.MG.029496-9.01 | B280: 29496 | C280: UTE | D280: Aeroporto de Montes Claros - Mário Ribeiro | E280: 003522940002E3 | F280: Empresa Brasileira de Infra-Estrutura Aeroportuária | G280: 100 | H280: PJ | J280: Normal | K280: Sim | L280: Sim | M280: Operação
A281: UTE.PE.TO.029568-0.01 | B281: 29568 | C281: UTE | D281: Aeroporto de Palmas | G281: 100 | K281: Sim | L281: Sim | M281: Operação
A282: UTE.PE.TO.029568-0.01 | B282: 29568 | C282: UTE | D282: Aeroporto de Palmas | E282: 003522940002E3 | F282: Empresa Brasileira de Infra-Estrutura Aeroportuária | G282: 100 | H282: PJ | J282: Normal | K282: Sim | L282: Sim | M282: Operação
A283: UFV.RS.BA.049251-5.01 | B283: 49251 | C283: UFV | D283: Aeroporto De Salvador | E283: 27950582000123 | F283: Concessionaria Do Aeroporto de Salvador S.A. | G283: 100 | H283: PJ | J283: Normal | K283: Sim | L283: Sim | M283: Operação
A284: UTE.PE.SP.029347-4.01 | B284: 29347 | C284: UTE | D284: Aeroporto de São José dos Campos | G284: 100 | K284: Sim | L284: Sim | M284: Operação
A285: UTE.PE.SP.029347-4.01 | B285: 29347 | C285: UTE | D285: Aeroporto de São José dos Campos | E285: 003522940002E3 | F285: Empresa Brasileira de Infra-Estrutura Aeroportuária | G285: 100 | H285: PJ | J285: Normal | K285: Sim | L285: Sim | M285: Operação
A286: UTE.PE.AM.029318-0.01 | B286: 29318 | C286: UTE | D286: Aeroporto de Tefé | G286: 100 | K286: Sim | L286: Sim | M286: Operação
A287: UTE.PE.AM.029318-0.01 | B287: 29318 | C287: UTE | D287: Aeroporto de Tefé | E287: 003522940002E3 | F287: Empresa Brasileira de Infra-Estrutura Aeroportuária | G287: 100 | H287: PJ | J287: Normal | K287: Sim | L287: Sim | M287: Operação
A288: UTE.PE.PI.029446-2.01 | B288: 29446 | C288: UTE | D288: Aeroporto de Teresina - Senador Petrônio Portella | G288: 100 | K288: Sim | L288: Sim | M288: Operação
A289: UTE.PE.PI.029446-2.01 | B289: 29446 | C289: UTE | D289: Aeroporto de Teresina - Senador Petrônio Portella | E289: 003522940002E3 | F289: Empresa Brasileira de Infra-Estrutura Aeroportuária | G289: 100 | H289: PJ | J289: Normal | K289: Sim | L289: Sim | M289: Operação
A290: UTE.PE.MG.029571-0.01 | B290: 29571 | C290: UTE | D290: Aeroporto de Uberaba | G290: 100 | K290: Sim | L290: Sim | M290: Operação
A291: UTE.PE.MG.029571-0.01 | B291: 29571 | C291: UTE | D291: Aeroporto de Uberaba | E291: 003522940002E3 | F291: Empresa Brasileira de Infra-Estrutura Aeroportuária | G291: 100 | H291: PJ | J291: Normal | K291: Sim | L291: Sim | M291: Operação
A292: UTE.PE.MG.029570-1.01 | B292: 29570 | C292: UTE | D292: Aeroporto de Uberlândia | G292: 100 | K292: Sim | L292: Sim | M292: Operação
A293: UTE.PE.MG.029570-1.01 | B293: 29570 | C293: UTE | D293: Aeroporto de Uberlândia | E293: 003522940002E3 | F293: Empresa Brasileira de Infra-Estrutura Aeroportuária | G293: 100 | H293: PJ | J293: Normal | K293: Sim | L293: Sim | M293: Operação
A294: UTE.PE.SP.029385-7.01 | B294: 29385 | C294: UTE | D294: Aeroporto de Urubupungá | G294: 100 | K294: Sim | L294: Sim | M294: Operação
A295: UTE.PE.SP.029385-7.01 | B295: 29385 | C295: UTE | D295: Aeroporto de Urubupungá | E295: 003522940002E3 | F295: Empresa Brasileira de Infra-Estrutura Aeroportuária | G295: 100 | H295: PJ | J295: Normal | K295: Sim | L295: Sim | M295: Operação
A296: UTE.PE.ES.029530-2.01 | B296: 29530 | C296: UTE | D296: Aeroporto de Vitória | G296: 100 | K296: Sim | L296: Sim | M296: Operação
A297: UTE.PE.ES.029530-2.01 | B297: 29530 | C297: UTE | D297: Aeroporto de Vitória | E297: 003522940002E3 | F297: Empresa Brasileira de Infra-Estrutura Aeroportuária | G297: 100 | H297: PJ | J297: Normal | K297: Sim | L297: Sim | M297: Operação
A298: UTE.PE.PR.029378-4.01 | B298: 29378 | C298: UTE | D298: Aeroporto Internacional Afonso Pena | G298: 100 | K298: Sim | L298: Sim | M298: Operação
A299: UTE.PE.PR.029378-4.01 | B299: 29378 | C299: UTE | D299: Aeroporto Internacional Afonso Pena | E299: 003522940002E3 | F299: Empresa Brasileira de Infra-Estrutura Aeroportuária | G299: 100 | H299: PJ | J299: Normal | K299: Sim | L299: Sim | M299: Operação
A300: UTE.PE.RN.029312-1.01 | B300: 29312 | C300: UTE | D300: Aeroporto Internacional Augusto Severo - CUT | G300: 100 | K300: Sim | L300: Sim | M300: Operação
A301: UTE.PE.RN.029312-1.01 | B301: 29312 | C301: UTE | D301: Aeroporto Internacional Augusto Severo - CUT | E301: 003522940002E3 | F301: Empresa Brasileira de Infra-Estrutura Aeroportuária | G301: 100 | H301: PJ | J301: Normal | K301: Sim | L301: Sim | M301: Operação
A302: UTE.PE.RN.029311-3.01 | B302: 29311 | C302: UTE | D302: Aeroporto Internacional Augusto Severo - SCI | G302: 100 | K302: Sim | L302: Sim | M302: Operação
A303: UTE.PE.RN.029311-3.01 | B303: 29311 | C303: UTE | D303: Aeroporto Internacional Augusto Severo - SCI | E303: 003522940002E3 | F303: Empresa Brasileira de Infra-Estrutura Aeroportuária | G303: 100 | H303: PJ | J303: Normal | K303: Sim | L303: Sim | M303: Operação
A304: UTE.PE.RN.029313-0.01 | B304: 29313 | C304: UTE | D304: Aeroporto Internacional Augusto Severo - Sub-Estação Prédio Anexo Operacional | G304: 100 | K304: Sim | L304: Sim | M304: Operação
A305: UTE.PE.RN.029313-0.01 | B305: 29313 | C305: UTE | D305: Aeroporto Internacional Augusto Severo - Sub-Estação Prédio Anexo Operacional | E305: 003522940002E3 | F305: Empresa Brasileira de Infra-Estrutura Aeroportuária | G305: 100 | H305: PJ | J305: Normal | K305: Sim | L305: Sim | M305: Operação
A306: UTE.PE.RR.029314-8.01 | B306: 29314 | C306: UTE | D306: Aeroporto Internacional de Boa Vista | G306: 100 | K306: Sim | L306: Sim | M306: Operação
A307: UTE.PE.RR.029314-8.01 | B307: 29314 | C307: UTE | D307: Aeroporto Internacional de Boa Vista | E307: 003522940002E3 | F307: Empresa Brasileira de Infra-Estrutura Aeroportuária | G307: 100 | H307: PJ | J307: Normal | K307: Sim | L307: Sim | M307: Operação
A308: UTE.PE.DF.029569-8.01 | B308: 29569 | C308: UTE | D308: Aeroporto Internacional de Brasília | G308: 100 | K308: Sim | L308: Sim | M308: Operação
A309: UTE.PE.DF.029569-8.01 | B309: 29569 | C309: UTE | D309: Aeroporto Internacional de Brasília | E309: 003522940002E3 | F309: Empresa Brasileira de Infra-Estrutura Aeroportuária | G309: 100 | H309: PJ | J309: Normal | K309: Sim | L309: Sim | M309: Operação
A310: UTE.PE.MS.029348-2.01 | B310: 29348 | C310: UTE | D310: Aeroporto Internacional de Campo Grande | G310: 100 | K310: Sim | L310: Sim | M310: Operação
A311: UTE.PE.MS.029348-2.01 | B311: 29348 | C311: UTE | D311: Aeroporto Internacional de Campo Grande | E311: 003522940002E3 | F311: Empresa Brasileira de Infra-Estrutura Aeroportuária | G311: 100 | H311: PJ | J311: Normal | K311: Sim | L311: Sim | M311: Operação
A312: UTE.PE.SP.029351-2.01 | B312: 29351 | C312: UTE | D312: Aeroporto Internacional de Congonhas - São Paulo | G312: 100 | K312: Sim | L312: Sim | M312: Operação
A313: UTE.PE.SP.029351-2.01 | B313: 29351 | C313: UTE | D313: Aeroporto Internacional de Congonhas - São Paulo | E313: 003522940002E3 | F313: Empresa Brasileira de Infra-Estrutura Aeroportuária | G313: 100 | H313: PJ | J313: Normal | K313: Sim | L313: Sim | M313: Operação
A314: UTE.PE.MS.029337-7.01 | B314: 29337 | C314: UTE | D314: Aeroporto Internacional de Corumbá | G314: 100 | K314: Sim | L314: Sim | M314: Operação
...
